{"data":{"index":1,"total":1,"posts":[{"title":"【开发杂记】第一次写 Hexo 插件","slug":"百味人生/数字与代码/【开发杂记】第一次写 Hexo 插件","date":"2024-04-28T16:27:23.000Z","updated":"2025-08-16T17:23:48.123Z","comments":true,"url":"p/2c7939aa/","excerpt":"","cover":"https://cdn.gallery.uuanqin.top/img/RTFM_header_2cover.webp","images":["https://github-readme-stats.uuanqin.top/api/pin/?username=uuanqin&amp;repo=hexo-filter-titlebased-link"],"categories":[{"name":"百味人生","slug":"百味人生","api":"api/categories/百味人生.json"},{"name":"数字与代码","slug":"百味人生/数字与代码","api":"api/categories/百味人生/数字与代码.json"}],"tags":[{"name":"Hexo","slug":"Hexo","api":"api/tags/Hexo.json"},{"name":"npm","slug":"npm","api":"api/tags/npm.json"},{"name":"Obsidian","slug":"Obsidian","api":"api/tags/Obsidian.json"},{"name":"开发杂记","slug":"开发杂记","api":"api/tags/开发杂记.json"},{"name":"正则表达式","slug":"正则表达式","api":"api/tags/正则表达式.json"}],"api":"api/posts/p/2c7939aa.json"},{"title":"本地文件夹的多端同步","slug":"核心协同/自动化/本地文件夹的多端同步","date":"2023-11-04T05:05:18.000Z","updated":"2024-11-01T18:30:21.751Z","comments":true,"url":"p/cce6330b/","excerpt":"","cover":"https://cdn.gallery.uuanqin.top/img/synccoverasf.webp","images":["https://cdn.gallery.uuanqin.top/img/202409050116532.webp","https://cdn.gallery.uuanqin.top/img/202409050116017.webp"],"categories":[{"name":"核心协同","slug":"核心协同","api":"api/categories/核心协同.json"},{"name":"自动化","slug":"核心协同/自动化","api":"api/categories/核心协同/自动化.json"}],"tags":[{"name":"实现","slug":"实现","api":"api/tags/实现.json"},{"name":"Obsidian","slug":"Obsidian","api":"api/tags/Obsidian.json"},{"name":"foldersync","slug":"foldersync","api":"api/tags/foldersync.json"},{"name":"SyncThing","slug":"SyncThing","api":"api/tags/SyncThing.json"},{"name":"OneDrive","slug":"OneDrive","api":"api/tags/OneDrive.json"},{"name":"Xmind","slug":"Xmind","api":"api/tags/Xmind.json"},{"name":"Android","slug":"Android","api":"api/tags/Android.json"},{"name":"Harmony","slug":"Harmony","api":"api/tags/Harmony.json"},{"name":"坚果云","slug":"坚果云","api":"api/tags/坚果云.json"}],"api":"api/posts/p/cce6330b.json"},{"title":"Butterfly 侧边栏实现 Obsidian 关系图谱","slug":"博客站点维护/Hexo/Butterfly 侧边栏实现 Obsidian 关系图谱","date":"2023-08-11T14:30:29.000Z","updated":"2025-01-14T12:40:33.890Z","comments":true,"url":"p/f6c0daf3/","excerpt":"","cover":"https://cdn.gallery.uuanqin.top/img/relationcover.png","images":["https://github-readme-stats.uuanqin.top/api/pin/?username=uuanqin&amp;repo=obsidian2cosma","https://cdn.gallery.uuanqin.top/img/20230811225333.png","https://cdn.gallery.uuanqin.top/img/20230811225838.png","https://cdn.gallery.uuanqin.top/img/20230811230008.png","https://cdn.gallery.uuanqin.top/img/20230811233922.png"],"categories":[{"name":"博客站点维护","slug":"博客站点维护","api":"api/categories/博客站点维护.json"},{"name":"Hexo","slug":"博客站点维护/Hexo","api":"api/categories/博客站点维护/Hexo.json"}],"tags":[{"name":"Python","slug":"Python","api":"api/tags/Python.json"},{"name":"HTML","slug":"HTML","api":"api/tags/HTML.json"},{"name":"CSS","slug":"CSS","api":"api/tags/CSS.json"},{"name":"GitHub","slug":"GitHub","api":"api/tags/GitHub.json"},{"name":"Markdown","slug":"Markdown","api":"api/tags/Markdown.json"},{"name":"Obsidian","slug":"Obsidian","api":"api/tags/Obsidian.json"},{"name":"Butterfly","slug":"Butterfly","api":"api/tags/Butterfly.json"},{"name":"NPM","slug":"NPM","api":"api/tags/NPM.json"},{"name":"YAML","slug":"YAML","api":"api/tags/YAML.json"},{"name":"Cosma","slug":"Cosma","api":"api/tags/Cosma.json"},{"name":"script","slug":"script","api":"api/tags/script.json"},{"name":"项目","slug":"项目","api":"api/tags/项目.json"}],"api":"api/posts/p/f6c0daf3.json"},{"title":"Obsidian Internal links 双向链接渲染解决方案","slug":"Archive/OutOfDate/Obsidian Internal links 双向链接渲染解决方案","date":"2023-08-01T03:34:33.000Z","updated":"2024-10-02T15:59:37.787Z","comments":true,"url":"p/7f51af81/","excerpt":"","cover":"https://cdn.gallery.uuanqin.top/img/new-out-of-date-cover.png","images":[],"categories":[{"name":"Archive","slug":"Archive","api":"api/categories/Archive.json"},{"name":"OutOfDate","slug":"Archive/OutOfDate","api":"api/categories/Archive/OutOfDate.json"}],"tags":[{"name":"JavaScript","slug":"JavaScript","api":"api/tags/JavaScript.json"},{"name":"Markdown","slug":"Markdown","api":"api/tags/Markdown.json"},{"name":"OFM","slug":"OFM","api":"api/tags/OFM.json"},{"name":"Obsidian","slug":"Obsidian","api":"api/tags/Obsidian.json"}],"api":"api/posts/p/7f51af81.json"},{"title":"Hexo 博客适配 Obsidian 新语法","slug":"博客站点维护/Hexo/Hexo 博客适配 Obsidian 新语法","date":"2023-08-01T03:34:33.000Z","updated":"2025-09-13T11:04:06.873Z","comments":true,"url":"p/d4bc55f2/","excerpt":"","cover":"https://cdn.gallery.uuanqin.top/img/hexoobsidian-Grammar.webp","images":["https://github-readme-stats.uuanqin.top/api/pin/?username=uuanqin&amp;repo=hexo-filter-titlebased-link","https://cdn.gallery.uuanqin.top/img/202411272304588.webp","https://cdn.gallery.uuanqin.top/img/202411272305682.webp","https://github-readme-stats.uuanqin.top/api/pin/?username=uuanqin&amp;repo=markdown-it-obsidian-imgsize"],"categories":[{"name":"博客站点维护","slug":"博客站点维护","api":"api/categories/博客站点维护.json"},{"name":"Hexo","slug":"博客站点维护/Hexo","api":"api/categories/博客站点维护/Hexo.json"}],"tags":[{"name":"CSS","slug":"CSS","api":"api/tags/CSS.json"},{"name":"Hexo","slug":"Hexo","api":"api/tags/Hexo.json"},{"name":"Markdown","slug":"Markdown","api":"api/tags/Markdown.json"},{"name":"GFM","slug":"GFM","api":"api/tags/GFM.json"},{"name":"OFM","slug":"OFM","api":"api/tags/OFM.json"},{"name":"Obsidian","slug":"Obsidian","api":"api/tags/Obsidian.json"},{"name":"Butterfly","slug":"Butterfly","api":"api/tags/Butterfly.json"},{"name":"NPM","slug":"NPM","api":"api/tags/NPM.json"},{"name":"Nodejs","slug":"Nodejs","api":"api/tags/Nodejs.json"},{"name":"cmd","slug":"cmd","api":"api/tags/cmd.json"},{"name":"plugin","slug":"plugin","api":"api/tags/plugin.json"}],"api":"api/posts/p/d4bc55f2.json"},{"title":"构建 Obsidian 的 Hexo 写作工作流","slug":"核心协同/构建 Obsidian 的 Hexo 写作工作流","date":"2023-06-01T14:22:07.000Z","updated":"2025-01-11T19:44:30.200Z","comments":true,"url":"p/51890a9/","excerpt":"","cover":"https://cdn.gallery.uuanqin.top/img/hexoobsidian-cowork.webp","images":["https://cdn.gallery.uuanqin.top/img/20230601235734.png"],"categories":[{"name":"核心协同","slug":"核心协同","api":"api/categories/核心协同.json"}],"tags":[{"name":"Hexo","slug":"Hexo","api":"api/tags/Hexo.json"},{"name":"Markdown","slug":"Markdown","api":"api/tags/Markdown.json"},{"name":"Typora","slug":"Typora","api":"api/tags/Typora.json"},{"name":"Obsidian","slug":"Obsidian","api":"api/tags/Obsidian.json"}],"api":"api/posts/p/51890a9.json"},{"title":"在 Obsidian 和 Hexo 两端使用 PlantUML","slug":"Archive/OutOfDate/在 Obsidian 和 Hexo 两端使用 PlantUML","date":"2023-06-01T14:22:07.000Z","updated":"2024-12-23T17:48:11.625Z","comments":true,"url":"p/a94e3d44/","excerpt":"","cover":"https://cdn.gallery.uuanqin.top/img/new-out-of-date-cover.png","images":["https://cdn.gallery.uuanqin.top/img/202412240052606.webp","https://cdn.gallery.uuanqin.top/img/部署失败6546565132.webp","https://cdn.gallery.uuanqin.top/img/20230910155117.webp","https://cdn.gallery.uuanqin.top/img/20230910153438.webp"],"categories":[{"name":"Archive","slug":"Archive","api":"api/categories/Archive.json"},{"name":"OutOfDate","slug":"Archive/OutOfDate","api":"api/categories/Archive/OutOfDate.json"}],"tags":[{"name":"Obsidian","slug":"Obsidian","api":"api/tags/Obsidian.json"},{"name":"PlantUML","slug":"PlantUML","api":"api/tags/PlantUML.json"}],"api":"api/posts/p/a94e3d44.json"},{"title":"双链渲染测试","slug":"核心协同/双链渲染测试","date":"2023-06-01T14:06:07.000Z","updated":"2025-09-13T10:56:31.421Z","comments":true,"url":"p/76288ef3/","excerpt":"","cover":"https://cdn.gallery.uuanqin.top/img/202408031543869.webp","images":["https://github-readme-stats.uuanqin.top/api/pin/?username=uuanqin&amp;repo=hexo-filter-titlebased-link","https://commonmark.org/help/images/favicon.png"],"categories":[{"name":"核心协同","slug":"核心协同","api":"api/categories/核心协同.json"}],"tags":[{"name":"源码案例驱动","slug":"源码案例驱动","api":"api/tags/源码案例驱动.json"},{"name":"Markdown","slug":"Markdown","api":"api/tags/Markdown.json"},{"name":"Typora","slug":"Typora","api":"api/tags/Typora.json"},{"name":"GFM","slug":"GFM","api":"api/tags/GFM.json"},{"name":"OFM","slug":"OFM","api":"api/tags/OFM.json"},{"name":"Obsidian","slug":"Obsidian","api":"api/tags/Obsidian.json"},{"name":"Github","slug":"Github","api":"api/tags/Github.json"}],"api":"api/posts/p/76288ef3.json"},{"title":"Markdown 渲染测试","slug":"核心协同/Markdown 渲染测试","date":"2023-06-01T14:06:06.000Z","updated":"2025-01-11T18:53:10.362Z","comments":true,"url":"p/3c4a82e6/","excerpt":"","cover":"https://cdn.gallery.uuanqin.top/img/mdcover65465.png","images":["https://commonmark.org/help/images/favicon.png"],"categories":[{"name":"核心协同","slug":"核心协同","api":"api/categories/核心协同.json"}],"tags":[{"name":"源码案例驱动","slug":"源码案例驱动","api":"api/tags/源码案例驱动.json"},{"name":"Markdown","slug":"Markdown","api":"api/tags/Markdown.json"},{"name":"Typora","slug":"Typora","api":"api/tags/Typora.json"},{"name":"GFM","slug":"GFM","api":"api/tags/GFM.json"},{"name":"OFM","slug":"OFM","api":"api/tags/OFM.json"},{"name":"Obsidian","slug":"Obsidian","api":"api/tags/Obsidian.json"},{"name":"Microsoft","slug":"Microsoft","api":"api/tags/Microsoft.json"},{"name":"Github","slug":"Github","api":"api/tags/Github.json"},{"name":"Katex","slug":"Katex","api":"api/tags/Katex.json"}],"api":"api/posts/p/3c4a82e6.json"}],"info":{"type":"tag","name":"Obsidian","slug":"Obsidian"}},"api":"api/tags/Obsidian/page.1.json"}