{"data":{"index":1,"total":1,"posts":[{"title":"UML 中类图与类的关系","slug":"高质量代码及设计模式/UML 中类图与类的关系","date":"2025-06-18T02:32:48.000Z","updated":"2025-08-07T14:12:20.324Z","comments":true,"url":"p/25e0b352/","excerpt":"","cover":"https://cdn.gallery.uuanqin.top/img/202506181034799.webp","images":["https://cdn.gallery.uuanqin.top/img/20231228170613.webp","https://cdn.gallery.uuanqin.top/img/20231227210050.webp","https://cdn.gallery.uuanqin.top/img/20231228170714.webp","https://cdn.gallery.uuanqin.top/img/20231228170856.webp","https://cdn.gallery.uuanqin.top/img/202506180952446.webp","https://cdn.gallery.uuanqin.top/img/202506180953150.webp","https://cdn.gallery.uuanqin.top/img/202506180958167.webp","https://cdn.gallery.uuanqin.top/img/7d51a77f-e555-48eb-8844-a481853081a9.webp","https://cdn.gallery.uuanqin.top/img/5029c884-95a8-47de-81a5-beb7929cacef.webp","https://cdn.gallery.uuanqin.top/img/202506181027467.webp","https://cdn.gallery.uuanqin.top/img/7f440eba-ad8e-4121-bb0f-b67ed7cf0dd8.webp","https://cdn.gallery.uuanqin.top/img/3be12571-32ab-4e30-96ce-42876bdf6bc7.webp","https://cdn.gallery.uuanqin.top/img/6b8635d8-b6a5-4909-b519-9df1b2f88191.webp","https://cdn.gallery.uuanqin.top/img/20231228172125.webp","https://cdn.gallery.uuanqin.top/img/b6c27425-3041-4c3e-9f82-9bcbb76d70b7.webp","https://cdn.gallery.uuanqin.top/img/202506181035026.webp","https://cdn.gallery.uuanqin.top/img/20231228172604.webp","https://cdn.gallery.uuanqin.top/img/c1b49bbe-dd98-46af-8330-06d1a8d24795.webp","https://cdn.gallery.uuanqin.top/img/20231228180237.webp","https://cdn.gallery.uuanqin.top/img/202506181016224.webp","https://cdn.gallery.uuanqin.top/img/7e07973a-e3be-4eba-bb7f-11b1ffaf4c70.webp","https://cdn.gallery.uuanqin.top/img/20231228180554.webp","https://cdn.gallery.uuanqin.top/img/9d27f4cc-b11a-40f4-bdde-eb0fb2eeb328.webp","https://cdn.gallery.uuanqin.top/img/202506181023928.webp","https://cdn.gallery.uuanqin.top/img/b2b6d8be-6627-453c-b6aa-abb6eb978970.webp","https://cdn.gallery.uuanqin.top/img/20231228182007.webp","https://cdn.gallery.uuanqin.top/img/ec8a73fa-453f-48d9-b8f6-9b6ffd745cf4.webp","https://cdn.gallery.uuanqin.top/img/202506181026778.webp","https://cdn.gallery.uuanqin.top/img/202506181036526.webp","https://cdn.gallery.uuanqin.top/img/202506181026837.webp","https://cdn.gallery.uuanqin.top/img/202506181029024.webp","https://cdn.gallery.uuanqin.top/img/202506181030399.webp"],"categories":[{"name":"高质量代码及设计模式","slug":"高质量代码及设计模式","api":"api/categories/高质量代码及设计模式.json"}],"tags":[{"name":"Java","slug":"Java","api":"api/tags/Java.json"},{"name":"C++","slug":"C","api":"api/tags/C.json"},{"name":"UML","slug":"UML","api":"api/tags/UML.json"},{"name":"类图","slug":"类图","api":"api/tags/类图.json"}],"api":"api/posts/p/25e0b352.json"},{"title":"STM32+ESP8266+MQTT 实现阿里云温湿度监控及 LED 点灯（FreeRTOS+标准库 or HAL）","slug":"嵌入式/STM32+ESP8266+MQTT 实现阿里云温湿度监控及 LED 点灯（FreeRTOS+标准库 or HAL）","date":"2024-04-05T04:49:50.000Z","updated":"2024-12-23T17:46:36.559Z","comments":true,"url":"p/de31d8e3/","excerpt":"","cover":"https://cdn.gallery.uuanqin.top/img/20240405161606.webp","images":["https://cdn.gallery.uuanqin.top/img/20240630000720.webp","https://cdn.gallery.uuanqin.top/img/20240630135721.webp","https://cdn.gallery.uuanqin.top/img/202412240142627.webp","https://cdn.gallery.uuanqin.top/img/202412240142103.webp","https://cdn.gallery.uuanqin.top/img/202412240143263.webp","https://cdn.gallery.uuanqin.top/img/20240405135040.webp","https://cdn.gallery.uuanqin.top/img/20240405135115.webp","https://cdn.gallery.uuanqin.top/img/20240405135235.webp","https://cdn.gallery.uuanqin.top/img/20240405135609.webp","https://cdn.gallery.uuanqin.top/img/20240405135735.webp","https://cdn.gallery.uuanqin.top/img/20240405135903.webp","https://cdn.gallery.uuanqin.top/img/20240405135956.webp","https://cdn.gallery.uuanqin.top/img/20240405140057.webp","https://cdn.gallery.uuanqin.top/img/20240405140129.webp","https://cdn.gallery.uuanqin.top/img/20240405140450.webp","https://cdn.gallery.uuanqin.top/img/20240405140617.webp","https://cdn.gallery.uuanqin.top/img/20240405140657.webp","https://cdn.gallery.uuanqin.top/img/20240405140802.webp","https://cdn.gallery.uuanqin.top/img/20240405140841.webp","https://cdn.gallery.uuanqin.top/img/20240405140944.webp","https://cdn.gallery.uuanqin.top/img/20240405141607.webp","https://cdn.gallery.uuanqin.top/img/20240405141654.webp","https://cdn.gallery.uuanqin.top/img/20240405142608.webp","https://cdn.gallery.uuanqin.top/img/20240405142728.webp","https://cdn.gallery.uuanqin.top/img/20240405142832.webp","https://cdn.gallery.uuanqin.top/img/20240405143044.webp","https://cdn.gallery.uuanqin.top/img/20240405143246.webp","https://cdn.gallery.uuanqin.top/img/20240405144051.webp","https://cdn.gallery.uuanqin.top/img/20240405143449.webp","https://cdn.gallery.uuanqin.top/img/20240405143533.webp","https://cdn.gallery.uuanqin.top/img/20240405143718.webp","https://cdn.gallery.uuanqin.top/img/20240405152014.webp"],"categories":[{"name":"嵌入式","slug":"嵌入式","api":"api/categories/嵌入式.json"}],"tags":[{"name":"C","slug":"C","api":"api/tags/C.json"},{"name":"阿里云","slug":"阿里云","api":"api/tags/阿里云.json"},{"name":"DHT11","slug":"DHT11","api":"api/tags/DHT11.json"},{"name":"STM32","slug":"STM32","api":"api/tags/STM32.json"},{"name":"HAL","slug":"HAL","api":"api/tags/HAL.json"},{"name":"ESP8266","slug":"ESP8266","api":"api/tags/ESP8266.json"},{"name":"MQTT","slug":"MQTT","api":"api/tags/MQTT.json"},{"name":"STM32CubeMX","slug":"STM32CubeMX","api":"api/tags/STM32CubeMX.json"},{"name":"FreeRTOS","slug":"FreeRTOS","api":"api/tags/FreeRTOS.json"},{"name":"UML","slug":"UML","api":"api/tags/UML.json"}],"api":"api/posts/p/de31d8e3.json"}],"info":{"type":"tag","name":"UML","slug":"UML"}},"api":"api/tags/UML/page.1.json"}