{"data":{"title":"个人独立申请软著流程","slug":"百味人生/社会生活/个人独立申请软著流程","description":"分享个人申请独立开发软件的软件著作权过程。","date":"2023-05-31T09:53:26.000Z","updated":"2024-08-08T09:21:05.104Z","language":"zh-CN","comments":true,"url":"p/511c30b3/","cover":"https://cdn.gallery.uuanqin.top/img/cpcccover.webp","images":[],"content":"<p>写毕业设计之前就有个想法为我自己开发的系统申请软件著作权，现在动手尝试，将主要步骤记录如下。</p>\n\n<div class=\"callout\" data-callout=\"hint\">\n<div class=\"callout-title\">\n<div class=\"callout-title-icon\">\n<svg xmlns=\"http://www.w3.org/2000/svg\" width=\"24\" height=\"24\" viewBox=\"0 0 24 24\" fill=\"none\" stroke=\"currentColor\" stroke-width=\"2\" stroke-linecap=\"round\" stroke-linejoin=\"round\" class=\"lucide lucide-flame\"><path d=\"M8.5 14.5A2.5 2.5 0 0 0 11 12c0-1.38-.5-2-1-3-1.072-2.143-.224-4.054 2-6 .5 2.5 2 4.9 4 6.5 2 1.6 3 3.5 3 5.5a7 7 0 1 1-14 0c0-1.153.433-2.294 1-3a2.5 2.5 0 0 0 2.5 2.5z\"/></svg>\n</div>\n<div class=\"callout-title-inner\">本篇文章以个人申请方式（个人开发）介绍过程，合作开发、学校署名等问题不在本文范围内。</div>\n</div>\n<div class=\"callout-content\"><p></p>\n</div></div><p>官网：<a href=\"https://www.ccopyright.com.cn/\">中国版权保护中心 (ccopyright.com.cn)</a></p>\n<h1 id=\"前言新的申请流程\"><a class=\"markdownIt-Anchor\" href=\"#前言新的申请流程\"></a> 前言：新的申请流程</h1>\n<p>我发现这个官网会莫名抽风，各种连接错误、系统错误和卡顿。然后在登记过程（5 月 31 日）中，每一次提交的申请会出现不同的流程和页面 UI。有时候给你邮寄提示，有时候又没有，并多出签章页打印环节而取消。当我隐隐约约觉察是不是流程改了，就随手翻翻通知。发现 5 月 25 日新通知 <sup class=\"footnote-ref\"><a href=\"#fn1\" id=\"fnref1\">[1]</a></sup>：</p>\n<p><img src= \"/image/loading.gif\" data-lazy-src=\"https://cdn.gallery.uuanqin.top/img/image-20230601115747781.png\" alt=\"image-20230601115747781\" /></p>\n<p>woc🤬，怪不得服务器抽风一阵后系统大变样。流程确实改了，这也说明网上的经验全没用了，接下来我的探索成果将是最早一批的改版经验！（后果：白花 10 块钱印了一堆废纸）</p>\n<p>以下是一张未改版前宝贵截图：</p>\n<img src= \"/image/loading.gif\" data-lazy-src=\"https://cdn.gallery.uuanqin.top/img/image-20230601120140239.png\" alt=\"image-20230601120140239\" style=\"zoom:50%;\" />\n<h1 id=\"注册账号并实名认证新用户\"><a class=\"markdownIt-Anchor\" href=\"#注册账号并实名认证新用户\"></a> 注册账号并实名认证（新用户）</h1>\n<p>首先登录官网 <a href=\"https://www.ccopyright.com.cn/\">中国版权保护中心 (ccopyright.com.cn)</a> 注册账号。</p>\n<p>注册成功后会有实名认证提示，也可以在账号管理 -&gt;实名认证处进行认证。</p>\n<p>需要准备好：身份证人像照、身份证国徽照、手持身份证自拍三张电子照片，要上传。</p>\n<blockquote>\n<p>实名认证填写的信息要和照片相符，不管你实际户籍移到哪里，身份证上写你是哪里的就填哪里的。我就是因为这个原因被“退货”了一下。</p>\n</blockquote>\n<p>认证失败也没关系，修正好资料就行。</p>\n<h1 id=\"准备好文档\"><a class=\"markdownIt-Anchor\" href=\"#准备好文档\"></a> 准备好文档</h1>\n<p>请详细阅读：<a href=\"https://www.ccopyright.com.cn/index.php?optionid=1080\">所需文件-中国版权保护中心 (ccopyright.com.cn)</a></p>\n<p>我准备的材料：</p>\n<ul>\n<li>文档鉴别材料 pdf x1 份</li>\n<li>源代码 pdf x1 份</li>\n</ul>\n<p>再提醒一些注意事项：</p>\n<ul>\n<li>除封面外每页有页眉，页眉标文章标题</li>\n<li>右上角为页码</li>\n<li>版本号 1.0、V1.0 要分清</li>\n<li>格式为 pdf</li>\n</ul>\n<p>源代码文档如何保证一页 50 行：</p>\n<ul>\n<li>\n<p>查看行数：word 中全选一页内容，点击左下角字数统计信息查看</p>\n<img src= \"/image/loading.gif\" data-lazy-src=\"https://cdn.gallery.uuanqin.top/img/image-20230531183332051.png\" alt=\"image-20230531183332051\" style=\"zoom: 80%;\" />\n</li>\n<li>\n<p>格式：字体 Time New Roman 五号，间距 固定值 13.9 磅</p>\n<p><img src= \"/image/loading.gif\" data-lazy-src=\"https://cdn.gallery.uuanqin.top/img/image-20230531183623863.png\" alt=\"image-20230531183623863\" width=\"425px\" /></p>\n</li>\n</ul>\n<p>页眉设置分享：</p>\n<ul>\n<li>\n<p>Word 中页眉“文档标题和页码同时存在”的设置方法：双击页眉进入页眉编辑后，输入文章标题。打开菜单：插入 -&gt;页码当前位置，即可插入页码。控制空格使得页码和页眉同时存在。</p>\n</li>\n<li>\n<p>Latex 页眉。因为我是套用 TJU 论文模板的，我也搞不清楚，弄着弄着就得了：</p>\n<figure class=\"highlight latex\"><table><tr><td class=\"gutter\"><pre><span class=\"line\">1</span><br><span class=\"line\">2</span><br><span class=\"line\">3</span><br><span class=\"line\">4</span><br><span class=\"line\">5</span><br><span class=\"line\">6</span><br><span class=\"line\">7</span><br><span class=\"line\">8</span><br><span class=\"line\">9</span><br><span class=\"line\">10</span><br><span class=\"line\">11</span><br><span class=\"line\">12</span><br><span class=\"line\">13</span><br><span class=\"line\">14</span><br><span class=\"line\">15</span><br><span class=\"line\">16</span><br><span class=\"line\">17</span><br></pre></td><td class=\"code\"><pre><span class=\"line\"><span class=\"keyword\">\\pagestyle</span>&#123;fancy&#125;                             \t<span class=\"comment\">% 设置正文眉页脚风格</span></span><br><span class=\"line\">    <span class=\"keyword\">\\fancyhead</span>[R]&#123;<span class=\"keyword\">\\thepage</span>&#125;            \t\t\t<span class=\"comment\">% 页眉格式</span></span><br><span class=\"line\">    <span class=\"keyword\">\\fancyhead</span>[C]&#123;XXX系统~V1.0~设计文档&#125;</span><br><span class=\"line\">    <span class=\"keyword\">\\fancyhead</span>[L]&#123;&#125;</span><br><span class=\"line\">    <span class=\"keyword\">\\fancyfoot</span>[C]&#123;&#125;           \t\t\t\t\t<span class=\"comment\">% 页脚格式</span></span><br><span class=\"line\">    <span class=\"keyword\">\\renewcommand</span>&#123;<span class=\"keyword\">\\headrulewidth</span>&#125;&#123;0.5pt&#125;</span><br><span class=\"line\">    <span class=\"keyword\">\\renewcommand</span>&#123;<span class=\"keyword\">\\footrulewidth</span>&#125;&#123;0pt&#125;</span><br><span class=\"line\"></span><br><span class=\"line\"><span class=\"keyword\">\\fancypagestyle</span>&#123;plain&#125;&#123;\t\t\t\t\t<span class=\"comment\">% 设置章首眉页脚风格</span></span><br><span class=\"line\">  <span class=\"keyword\">\\pagestyle</span>&#123;fancy&#125;&#123;</span><br><span class=\"line\">    <span class=\"keyword\">\\fancyhead</span>[R]&#123;<span class=\"keyword\">\\thepage</span>&#125;           \t<span class=\"comment\">% 页眉格式</span></span><br><span class=\"line\">    <span class=\"keyword\">\\fancyhead</span>[C]&#123;XXX系统~V1.0~设计文档&#125;</span><br><span class=\"line\">    <span class=\"keyword\">\\fancyhead</span>[L]&#123;&#125;</span><br><span class=\"line\">    <span class=\"keyword\">\\fancyfoot</span>[C]&#123;&#125;           \t\t\t<span class=\"comment\">% 页脚格式</span></span><br><span class=\"line\">    <span class=\"keyword\">\\renewcommand</span>&#123;<span class=\"keyword\">\\headrulewidth</span>&#125;&#123;0.5pt&#125;</span><br><span class=\"line\">    <span class=\"keyword\">\\renewcommand</span>&#123;<span class=\"keyword\">\\footrulewidth</span>&#125;&#123;0pt&#125;</span><br><span class=\"line\">  &#125;</span><br></pre></td></tr></table></figure>\n</li>\n</ul>\n<h1 id=\"网上申请\"><a class=\"markdownIt-Anchor\" href=\"#网上申请\"></a> 网上申请</h1>\n<p>按提示填好信息。</p>\n<p>申请完成后，会有打印签章页环节（2023 年 6 月新流程）。</p>\n<p><img src= \"/image/loading.gif\" data-lazy-src=\"https://cdn.gallery.uuanqin.top/img/QQ截图20230601114103.png\" alt=\"QQ截图20230601114103.png\" width=\"625px\" /></p>\n<p><img src= \"/image/loading.gif\" data-lazy-src=\"https://cdn.gallery.uuanqin.top/img/image-20230601121053373.png\" alt=\"img\" width=\"600px\" /></p>\n<p>我的做法是现在签章页后使用电子签名，之后上传并提交申请就行。</p>\n<p><img src= \"/image/loading.gif\" data-lazy-src=\"https://cdn.gallery.uuanqin.top/img/image-20230601142559534.png\" alt=\"img\" width=\"600px\" /></p>\n<blockquote>\n<p>注意到，新版本中删除申请更方便了</p>\n</blockquote>\n<p>20 天后进入受理流程：</p>\n<p><img src= \"/image/loading.gif\" data-lazy-src=\"https://cdn.gallery.uuanqin.top/img/20230622110009.png\" alt=\"image.png\" /></p>\n<p><img src= \"/image/loading.gif\" data-lazy-src=\"https://cdn.gallery.uuanqin.top/img/20230622110043.png\" alt=\"image.png\" /></p>\n<h1 id=\"接收\"><a class=\"markdownIt-Anchor\" href=\"#接收\"></a> 接收</h1>\n<p>经过漫长的等待，与 2023 年 8 月 1 日受理并审查完成，不过它颁发的是一个电子件。怪不得之前整个 7 月份查看时收件人地址变得不可更改了，最后直接就消失了。</p>\n<p><img src= \"/image/loading.gif\" data-lazy-src=\"https://cdn.gallery.uuanqin.top/img/20230801215656.png\" alt=\"image.png\" /></p>\n<p>这么说来整个无纸化流程方便很多，我也算是第一批使用新流程的用户了吧。</p>\n<p>当当当当！</p>\n<p><img src= \"/image/loading.gif\" data-lazy-src=\"https://cdn.gallery.uuanqin.top/img/rzzz.jpg\" alt=\"rzzz.jpg\" width=\"400px\" /></p>\n<h1 id=\"后记\"><a class=\"markdownIt-Anchor\" href=\"#后记\"></a> 后记</h1>\n<p>注意到网站 Logo 换了，丑了。由于网站处于改版期，整个网站功能板块、交互、界面半新半旧的，弄得我好别扭。</p>\n<p><img src= \"/image/loading.gif\" data-lazy-src=\"https://cdn.gallery.uuanqin.top/img/20230801221819.png\" alt=\"image.png\" width=\"500px\" /></p>\n<p><img src= \"/image/loading.gif\" data-lazy-src=\"https://cdn.gallery.uuanqin.top/img/20230801221807.png\" alt=\"image.png\" width=\"500px\" /></p>\n<p>看了通知，原来是热乎的 <sup class=\"footnote-ref\"><a href=\"#fn2\" id=\"fnref2\">[2]</a></sup>。</p>\n<h1 id=\"本文参考\"><a class=\"markdownIt-Anchor\" href=\"#本文参考\"></a> 本文参考</h1>\n<ul>\n<li><a href=\"https://www.zhihu.com/search?q=%E4%B8%AA%E4%BA%BA%E7%94%B3%E8%AF%B7%E8%BD%AF%E4%BB%B6%E8%91%97%E4%BD%9C%E6%9D%83&amp;utm_content=search_history&amp;type=content\">个人申请软件著作权 - 搜索结果 - 知乎 (zhihu.com)</a></li>\n<li><a href=\"https://github.com/zephms/ccopyright-software-copyright-application/tree/main\">zephms/ccopyright-software-copyright-application: 中国版权保护中心 软件著作权申请教程 (github.com)</a></li>\n<li><a href=\"https://zhidao.baidu.com/question/274830328.html\">如何让页眉和页码同时显示_百度知道 (baidu.com)</a></li>\n<li><a href=\"https://blog.csdn.net/m0_57028150/article/details/129690954\">latex 章首添加页眉<em>latex 首页页眉</em>玛莎拉蒂的车轮的博客-CSDN 博客</a></li>\n<li><a href=\"https://zhuanlan.zhihu.com/p/114676221\">Latex 的页脚和页眉 - 知乎 (zhihu.com)</a></li>\n</ul>\n<hr class=\"footnotes-sep\" />\n<section class=\"footnotes\">\n<ol class=\"footnotes-list\">\n<li id=\"fn1\" class=\"footnote-item\"><p><a href=\"https://www.ccopyright.com.cn/index.php?optionid=998&amp;method=view&amp;optionid=998&amp;auto_id=1005\">关于软件版权登记网上办理试运行的通知-中心公告-中国版权保护中心 (ccopyright.com.cn)</a>： <a href=\"#fnref1\" class=\"footnote-backref\">↩︎</a></p>\n</li>\n<li id=\"fn2\" class=\"footnote-item\"><p><a href=\"https://www.ccopyright.com.cn/index.php?optionid=998&amp;method=view&amp;optionid=998&amp;auto_id=1026\">中国版权保护中心发布新形象标识-中心公告-中国版权保护中心 (ccopyright.com.cn)</a> <a href=\"#fnref2\" class=\"footnote-backref\">↩︎</a></p>\n</li>\n</ol>\n</section>\n","raw":"---\ntitle: 个人独立申请软著流程\ntags:\n  - 软著\ncover: 'https://cdn.gallery.uuanqin.top/img/cpcccover.webp'\ndescription: 分享个人申请独立开发软件的软件著作权过程。\ncategories:\n  - 百味人生\n  - 社会生活\nabbrlink: 511c30b3\ndate: 2023-05-31 17:53:26\n---\n\n写毕业设计之前就有个想法为我自己开发的系统申请软件著作权，现在动手尝试，将主要步骤记录如下。\n\n> [!hint] 本篇文章以个人申请方式（个人开发）介绍过程，合作开发、学校署名等问题不在本文范围内。\n\n官网：[中国版权保护中心 (ccopyright.com.cn)](https://www.ccopyright.com.cn/)\n\n# 前言：新的申请流程\n\n我发现这个官网会莫名抽风，各种连接错误、系统错误和卡顿。然后在登记过程（5 月 31 日）中，每一次提交的申请会出现不同的流程和页面 UI。有时候给你邮寄提示，有时候又没有，并多出签章页打印环节而取消。当我隐隐约约觉察是不是流程改了，就随手翻翻通知。发现 5 月 25 日新通知 [^new]：\n\n[^new]: [关于软件版权登记网上办理试运行的通知-中心公告-中国版权保护中心 (ccopyright.com.cn)](https://www.ccopyright.com.cn/index.php?optionid=998&method=view&optionid=998&auto_id=1005)：\n\n![image-20230601115747781](https://cdn.gallery.uuanqin.top/img/image-20230601115747781.png)\n\nwoc🤬，怪不得服务器抽风一阵后系统大变样。流程确实改了，这也说明网上的经验全没用了，接下来我的探索成果将是最早一批的改版经验！（后果：白花 10 块钱印了一堆废纸）\n\n以下是一张未改版前宝贵截图：\n\n<img src=\"https://cdn.gallery.uuanqin.top/img/image-20230601120140239.png\" alt=\"image-20230601120140239\" style=\"zoom:50%;\" />\n\n# 注册账号并实名认证（新用户）\n\n首先登录官网 [中国版权保护中心 (ccopyright.com.cn)](https://www.ccopyright.com.cn/) 注册账号。\n\n注册成功后会有实名认证提示，也可以在账号管理 ->实名认证处进行认证。\n\n需要准备好：身份证人像照、身份证国徽照、手持身份证自拍三张电子照片，要上传。\n\n> 实名认证填写的信息要和照片相符，不管你实际户籍移到哪里，身份证上写你是哪里的就填哪里的。我就是因为这个原因被“退货”了一下。\n\n认证失败也没关系，修正好资料就行。\n\n# 准备好文档\n\n请详细阅读：[所需文件-中国版权保护中心 (ccopyright.com.cn)](https://www.ccopyright.com.cn/index.php?optionid=1080)\n\n我准备的材料：\n\n- 文档鉴别材料 pdf x1 份\n- 源代码 pdf x1 份\n\n再提醒一些注意事项：\n\n- 除封面外每页有页眉，页眉标文章标题\n- 右上角为页码\n- 版本号 1.0、V1.0 要分清\n- 格式为 pdf\n\n源代码文档如何保证一页 50 行：\n\n- 查看行数：word 中全选一页内容，点击左下角字数统计信息查看\n\n  <img src=\"https://cdn.gallery.uuanqin.top/img/image-20230531183332051.png\" alt=\"image-20230531183332051\" style=\"zoom: 80%;\" />\n\n- 格式：字体 Time New Roman 五号，间距 固定值 13.9 磅\n\n  ![image-20230531183623863|425](https://cdn.gallery.uuanqin.top/img/image-20230531183623863.png)\n\n页眉设置分享：\n\n- Word 中页眉“文档标题和页码同时存在”的设置方法：双击页眉进入页眉编辑后，输入文章标题。打开菜单：插入 ->页码当前位置，即可插入页码。控制空格使得页码和页眉同时存在。\n- Latex 页眉。因为我是套用 TJU 论文模板的，我也搞不清楚，弄着弄着就得了：\n\n  ```latex\n  \\pagestyle{fancy}                             \t% 设置正文眉页脚风格\n      \\fancyhead[R]{\\thepage}            \t\t\t% 页眉格式\n      \\fancyhead[C]{XXX系统~V1.0~设计文档}\n      \\fancyhead[L]{}\n      \\fancyfoot[C]{}           \t\t\t\t\t% 页脚格式\n      \\renewcommand{\\headrulewidth}{0.5pt}\n      \\renewcommand{\\footrulewidth}{0pt}\n\n  \\fancypagestyle{plain}{\t\t\t\t\t% 设置章首眉页脚风格\n    \\pagestyle{fancy}{\n      \\fancyhead[R]{\\thepage}           \t% 页眉格式\n      \\fancyhead[C]{XXX系统~V1.0~设计文档}\n      \\fancyhead[L]{}\n      \\fancyfoot[C]{}           \t\t\t% 页脚格式\n      \\renewcommand{\\headrulewidth}{0.5pt}\n      \\renewcommand{\\footrulewidth}{0pt}\n    }\n  ```\n\n# 网上申请\n\n按提示填好信息。\n\n申请完成后，会有打印签章页环节（2023 年 6 月新流程）。\n\n![QQ截图20230601114103.png|625](https://cdn.gallery.uuanqin.top/img/QQ%E6%88%AA%E5%9B%BE20230601114103.png)\n\n![img|600](https://cdn.gallery.uuanqin.top/img/image-20230601121053373.png)\n\n我的做法是现在签章页后使用电子签名，之后上传并提交申请就行。\n\n![img|600](https://cdn.gallery.uuanqin.top/img/image-20230601142559534.png)\n\n> 注意到，新版本中删除申请更方便了\n\n20 天后进入受理流程：\n\n![image.png](https://cdn.gallery.uuanqin.top/img/20230622110009.png)\n\n![image.png](https://cdn.gallery.uuanqin.top/img/20230622110043.png)\n\n# 接收\n\n经过漫长的等待，与 2023 年 8 月 1 日受理并审查完成，不过它颁发的是一个电子件。怪不得之前整个 7 月份查看时收件人地址变得不可更改了，最后直接就消失了。\n\n![image.png](https://cdn.gallery.uuanqin.top/img/20230801215656.png)\n\n这么说来整个无纸化流程方便很多，我也算是第一批使用新流程的用户了吧。\n\n当当当当！\n\n![rzzz.jpg|400](https://cdn.gallery.uuanqin.top/img/rzzz.jpg)\n\n# 后记\n\n注意到网站 Logo 换了，丑了。由于网站处于改版期，整个网站功能板块、交互、界面半新半旧的，弄得我好别扭。\n\n![image.png|500](https://cdn.gallery.uuanqin.top/img/20230801221819.png)\n\n![image.png|500](https://cdn.gallery.uuanqin.top/img/20230801221807.png)\n\n看了通知，原来是热乎的 [^hot]。\n\n[^hot]: [中国版权保护中心发布新形象标识-中心公告-中国版权保护中心 (ccopyright.com.cn)](https://www.ccopyright.com.cn/index.php?optionid=998&method=view&optionid=998&auto_id=1026)\n\n# 本文参考\n\n- [个人申请软件著作权 - 搜索结果 - 知乎 (zhihu.com)](https://www.zhihu.com/search?q=个人申请软件著作权&utm_content=search_history&type=content)\n- [zephms/ccopyright-software-copyright-application: 中国版权保护中心 软件著作权申请教程 (github.com)](https://github.com/zephms/ccopyright-software-copyright-application/tree/main)\n- [如何让页眉和页码同时显示\\_百度知道 (baidu.com)](https://zhidao.baidu.com/question/274830328.html)\n- [latex 章首添加页眉*latex 首页页眉*玛莎拉蒂的车轮的博客-CSDN 博客](https://blog.csdn.net/m0_57028150/article/details/129690954)\n- [Latex 的页脚和页眉 - 知乎 (zhihu.com)](https://zhuanlan.zhihu.com/p/114676221)\n","categories":[{"name":"百味人生","api":"api/categories/百味人生.json"},{"name":"社会生活","api":"api/categories/百味人生/社会生活.json"}],"tags":[{"name":"软著","api":"api/tags/软著.json"}]},"api":"api/posts/p/511c30b3.json"}